tapioca_qualys_was/__init__.py
tapioca_qualys_was/resource_mapping.py
tapioca_qualys_was/tapioca_qualys_was.py
tapioca_qualys_was-0.9.dist-info/LICENSE
tapioca_qualys_was-0.9.dist-info/METADATA
tapioca_qualys_was-0.9.dist-info/WHEEL
tapioca_qualys_was-0.9.dist-info/top_level.txt
tapioca_qualys_was-0.9.dist-info/RECORD
