Metadata-Version: 2.1
Name: tapioca-qualys-was
Version: 0.9
Summary: qualys_was API wrapper using tapioca
Home-page: https://github.com/siteblindado/tapioca-qualys_was
Author: Site Blindado S.A.
Author-email: dev@siteblindado.com.br
License: MIT
Keywords: qualys_was
Platform: UNKNOWN
Classifier: Development Status :: 5 - Production/Stable
Classifier: Intended Audience :: Developers
Classifier: License :: OSI Approved :: MIT License
Classifier: Natural Language :: English
Classifier: Programming Language :: Python :: 2
Classifier: Programming Language :: Python :: 2.7
Classifier: Programming Language :: Python :: 3
Classifier: Programming Language :: Python :: 3.1
Classifier: Programming Language :: Python :: 3.2
Classifier: Programming Language :: Python :: 3.3
Classifier: Programming Language :: Python :: 3.4
Classifier: Programming Language :: Python :: 3.5
Classifier: Programming Language :: Python :: 3.6
Requires-Dist: tapioca-wrapper (<2)
